pyconometrics/__init__.py
pyconometrics/data.py
pyconometrics/ma.py
pyconometrics/metric.py
pyconometrics/model.py
pyconometrics-0.1.dist-info/METADATA
pyconometrics-0.1.dist-info/WHEEL
pyconometrics-0.1.dist-info/licenses/LICENSE
pyconometrics-0.1.dist-info/RECORD
