Metadata-Version: 2.1
Name: pyconometrics
Version: 0.1
Summary: A small package for econometrics and finance.
Project-URL: Homepage, https://github.com/wkflanders/pyconometrics
Project-URL: Bug Tracker, https://github.com/wkflanders/pyconometrics/issues
Author-email: wkflanders <wflanders@haverford.edu>
License: MIT License
Classifier: License :: OSI Approved :: MIT License
Classifier: Operating System :: OS Independent
Classifier: Programming Language :: Python :: 3
Requires-Python: >=3.7
Requires-Dist: numpy>=1.23.0
Requires-Dist: pandas-datareader>=0.10.0
Requires-Dist: pandas>=1.4.3
